CHANGES.txt
CONTRIBUTORS.txt
MANIFEST.in
README.txt
setup.cfg
setup.py
docs/HISTORY.txt
docs/INSTALL.txt
docs/LICENSE.GPL
docs/LICENSE.txt
gomobile/__init__.py
gomobile.supporter.egg-info/PKG-INFO
gomobile.supporter.egg-info/SOURCES.txt
gomobile.supporter.egg-info/dependency_links.txt
gomobile.supporter.egg-info/entry_points.txt
gomobile.supporter.egg-info/namespace_packages.txt
gomobile.supporter.egg-info/not-zip-safe
gomobile.supporter.egg-info/paster_plugins.txt
gomobile.supporter.egg-info/requires.txt
gomobile.supporter.egg-info/top_level.txt
gomobile/supporter/__init__.py
gomobile/supporter/config.py
gomobile/supporter/configure.zcml
gomobile/supporter/overrides.zcml
gomobile/supporter/discussion/__init__.py
gomobile/supporter/discussion/configure.zcml
gomobile/supporter/easytemplate/README.txt
gomobile/supporter/easytemplate/__init__.py
gomobile/supporter/easytemplate/configure.zcml
gomobile/supporter/easytemplate/overrider.py
gomobile/supporter/easytemplate/tests.py
gomobile/supporter/easytemplate/views.py
gomobile/supporter/easytemplate/templates/easytemplatemobile.pt
gomobile/supporter/feedfeeder/__init__.py
gomobile/supporter/feedfeeder/configure.zcml
gomobile/supporter/feedfeeder/feed-folder.pt
gomobile/supporter/feedfeeder/feed-item.pt
gomobile/supporter/feedfeeder/overrides.zcml
gomobile/supporter/feedfeeder/patches.py
gomobile/supporter/feedfeeder/views.py