Metadata-Version: 1.0
Name: gomobile.supporter
Version: 0.9.3
Summary: Add mobile support for various Plone add on products
Home-page: http://webandmobile.mfabrik.com
Author: mFabrik Research Oy
Author-email: research@mfabrik.com
License: GPL
Keywords: mobile plone python
Platform: UNKNOWN
Classifier: Framework :: Plone
Classifier: Intended Audience :: Developers
Classifier: Topic :: Software Development :: Libraries :: Python Modules
Classifier: License :: OSI Approved :: GNU General Public License (GPL)
